csv2cleartable/__init__.py
csv2cleartable-0.0.11.dist-info/LICENCE.txt
csv2cleartable-0.0.11.dist-info/METADATA
csv2cleartable-0.0.11.dist-info/WHEEL
csv2cleartable-0.0.11.dist-info/top_level.txt
csv2cleartable-0.0.11.dist-info/RECORD
